basicdate
