Metadata-Version: 1.1
Name: basicdate
Version: 0.7
Summary: A very basic set of Python classes for simple date manipulation
Home-page: https://github.com/GigiusB/basicdate
Author: Giovanni Bronzini
Author-email: g.bronzini@gmail.com
License: BSD 3-Clause
Keywords: date,util
Platform: UNKNOWN
Classifier: Development Status :: 3 - Alpha
Classifier: Framework :: Django
Classifier: License :: OSI Approved :: BSD License
Classifier: Natural Language :: English
Classifier: Programming Language :: Python :: 3.6
